[{"name": "Jujutsu Kaisen", "category": "Anime", "post_count": 3, "total_views": 403520, "total_likes": 109, "total_comments": 8, "video_count": 3, "first_collab": "2026-03-13", "videos": [{"video_id": "XKBgwSl-hUA", "url": "https://www.youtube.com/watch?v=XKBgwSl-hUA", "title": "KOLABORASI PUBG MOBILE x JUJUTSU KAISEN HADIR DI BATTLEGROUND!", "published_at": "2026-03-13", "view_count": 398662, "like_count": 26, "comment_count": 2, "thumbnail": "https://i.ytimg.com/vi/XKBgwSl-hUA/maxresdefault.jpg", "category": "Anime"}, {"video_id": "Eb_7guC7OtA", "url": "https://www.youtube.com/watch?v=Eb_7guC7OtA", "title": "Kolaborasi PUBG MOBILE x Jujutsu Kaisen Hadir di Battleground", "published_at": "2026-03-13", "view_count": 3087, "like_count": 73, "comment_count": 5, "thumbnail": "https://i.ytimg.com/vi/Eb_7guC7OtA/maxresdefault.jpg", "category": "Anime"}, {"video_id": "YuCac4QOLyc", "url": "https://www.youtube.com/watch?v=YuCac4QOLyc", "title": "PUBG MOBILE | Dapetin Set Spesial Jujutsu Kaisen Sekarang!", "published_at": "2026-03-13", "view_count": 1771, "like_count": 10, "comment_count": 1, "thumbnail": "https://i.ytimg.com/vi/YuCac4QOLyc/maxresdefault.jpg", "category": "Anime"}]}, {"name": "Punch Monkey", "category": "Other", "post_count": 1, "total_views": 3163, "total_likes": 29, "total_comments": 1, "video_count": 1, "first_collab": "2026-03-13", "videos": [{"video_id": "p8oAPnvOXNA", "url": "https://www.youtube.com/watch?v=p8oAPnvOXNA", "title": "PUBG MOBILE | We Loves You Punch Monkey", "published_at": "2026-03-13", "view_count": 3163, "like_count": 29, "comment_count": 1, "thumbnail": "https://i.ytimg.com/vi/p8oAPnvOXNA/maxresdefault.jpg", "category": "Other"}]}]